abstractagent/__init__.py
abstractagent/repl.py
abstractagent/adapters/__init__.py
abstractagent/adapters/codeact_runtime.py
abstractagent/adapters/memact_runtime.py
abstractagent/adapters/react_runtime.py
abstractagent/agents/__init__.py
abstractagent/agents/base.py
abstractagent/agents/codeact.py
abstractagent/agents/memact.py
abstractagent/agents/react.py
abstractagent/logic/__init__.py
abstractagent/logic/builtins.py
abstractagent/logic/codeact.py
abstractagent/logic/memact.py
abstractagent/logic/react.py
abstractagent/logic/types.py
abstractagent/sandbox/__init__.py
abstractagent/sandbox/interface.py
abstractagent/sandbox/local.py
abstractagent/scripts/__init__.py
abstractagent/scripts/lmstudio_tool_eval.py
abstractagent/tools/__init__.py
abstractagent/tools/code_execution.py
abstractagent/tools/self_improve.py
abstractagent-0.3.0.dist-info/licenses/LICENSE
abstractagent-0.3.0.dist-info/METADATA
abstractagent-0.3.0.dist-info/WHEEL
abstractagent-0.3.0.dist-info/entry_points.txt
abstractagent-0.3.0.dist-info/top_level.txt
abstractagent-0.3.0.dist-info/RECORD
