Metadata-Version: 2.4
Name: abstractagent
Version: 0.3.0
Summary: Agent implementations using AbstractRuntime and AbstractCore
Requires-Python: >=3.10
License-File: LICENSE
Requires-Dist: abstractcore[tools]
Requires-Dist: abstractruntime
Provides-Extra: dev
Requires-Dist: pytest>=7.0; extra == "dev"
Dynamic: license-file
